vincam/__init__.py
vincam/vincam.py
vincam/_libs/__init__.py
vincam/_libs/d3d11.py
vincam/_libs/dxgi.py
vincam/_libs/user32.py
vincam/core/__init__.py
vincam/core/device.py
vincam/core/duplicator.py
vincam/core/output.py
vincam/core/stagesurf.py
vincam/processor/__init__.py
vincam/processor/base.py
vincam/processor/cupy_processor.py
vincam/processor/numpy_processor.py
vincam/util/__init__.py
vincam/util/io.py
vincam/util/timer.py
vincam-7.8.9.dist-info/METADATA
vincam-7.8.9.dist-info/WHEEL
vincam-7.8.9.dist-info/top_level.txt
vincam-7.8.9.dist-info/RECORD
