Metadata-Version: 2.1
Name: vincam
Version: 7.8.9
Requires-Python: >=3.11
Requires-Dist: numpy
Requires-Dist: comtypes
